micro/__init__.py
micro/events/__init__.py
micro/events/publishers/__init__.py
micro/events/publishers/base.py
micro/events/publishers/registry.py
micro/fast/__init__.py
micro/jango/__init__.py
micro/jango/commands/__init__.py
micro/jango/commands/base.py
micro/jango/constants/__init__.py
micro/jango/constants/base.py
micro/jango/exceptions/__init__.py
micro/jango/exceptions/exception.py
micro/jango/exceptions/handler.py
micro/jango/middlewares/__init__.py
micro/jango/middlewares/api.py
micro/jango/middlewares/authentication.py
micro/jango/models/__init__.py
micro/jango/models/fields.py
micro/jango/models/history.py
micro/jango/models/manager.py
micro/jango/models/queryset.py
micro/jango/models/uuid.py
micro/jango/permissions/__init__.py
micro/jango/permissions/internal.py
micro/jango/renderers/__init__.py
micro/jango/renderers/json.py
micro/jango/serializers/__init__.py
micro/jango/serializers/base.py
micro/jango/serializers/fields.py
micro/jango/services/__init__.py
micro/jango/services/base.py
micro/jango/tests/__init__.py
micro/jango/tests/base.py
micro/jango/tests/conftest.py
micro/jango/utils/__init__.py
micro/jango/utils/utils.py
micro/jango/views/__init__.py
micro/jango/views/base.py
micro/patterns/__init__.py
micro/patterns/null.py
micro/patterns/saga.py
micro/services/__init__.py
micro/services/base.py
micro/services/registry.py
micro/utils/__init__.py
micro/utils/utils.py
microslac-0.0.20.dist-info/METADATA
microslac-0.0.20.dist-info/WHEEL
microslac-0.0.20.dist-info/RECORD
