Metadata-Version: 2.1
Name: microslac
Version: 0.0.20
Summary: 
Author: tanlda
Author-email: ledinhanhtan.stack@gmail.com
Requires-Python: >=3.10,<4.0
Classifier: Programming Language :: Python :: 3
Classifier: Programming Language :: Python :: 3.10
Classifier: Programming Language :: Python :: 3.11
Classifier: Programming Language :: Python :: 3.12
Requires-Dist: pyjwt (>=2.8.0,<3.0.0)
Requires-Dist: requests (>=2.31.0,<3.0.0)
Requires-Dist: shortuuid (>=1.0.13,<2.0.0)
